README
setup.py
twister.py
twister_game.egg-info/PKG-INFO
twister_game.egg-info/SOURCES.txt
twister_game.egg-info/dependency_links.txt
twister_game.egg-info/not-zip-safe
twister_game.egg-info/requires.txt
twister_game.egg-info/top_level.txt