Metadata-Version: 1.1
Name: twister-game
Version: 2.0
Summary: Twister
Home-page: http://bitbucket.org/albertnan/twister
Author: Albert Cervera i Areny
Author-email: albert@nan-tic.com
License: GPL-3
Download-URL: http://bitbucket.org/albertnan/twister
Keywords: twister game
Platform: any
Classifier: Development Status :: 5 - Production/Stable
Classifier: Environment :: Console
Classifier: Intended Audience :: End Users/Desktop
Classifier: License :: OSI Approved :: GNU General Public License (GPL)
Classifier: Natural Language :: English
Classifier: Operating System :: OS Independent
Classifier: Programming Language :: Python :: 3.5
Classifier: Topic :: Games/Entertainment
